scrnatools/__init__.py
scrnatools/_configs.py
scrnatools/_utils/__init__.py
scrnatools/_utils/_check_path.py
scrnatools/_utils/_fill_array.py
scrnatools/_utils/_type_check.py
scrnatools/plotting/__init__.py
scrnatools/plotting/_gene_density_plot.py
scrnatools/plotting/_gene_embedding.py
scrnatools/plotting/_gene_heatmap.py
scrnatools/plotting/_gene_violinplot.py
scrnatools/plotting/_isoform_qc_plot.py
scrnatools/plotting/_qc_plotting.py
scrnatools/qc/__init__.py
scrnatools/qc/_filter_cells.py
scrnatools/qc/_scrublet.py
scrnatools/tools/__init__.py
scrnatools/tools/_cell_type_similarity.py
scrnatools/tools/_cluster_de.py
scrnatools/tools/_create_cell_type_signature.py
scrnatools/tools/_create_isoform_lookup_tables.py
scrnatools/tools/_get_expression_matrix.py
scrnatools/tools/_get_immgen_similarity_signatures.py
scrnatools/tools/_isoform_preprocessing.py
scrnatools/tools/_load_isoform_lookup_tables.py
scrnatools/tools/_log_density_ratio.py
scrnatools/tools/_read_kallisto_tcc_matrix.py
scrnatools/tools/_save_isoform_lookup_tables.py
scrnatools-1.12.3.dist-info/LICENSE.txt
scrnatools-1.12.3.dist-info/METADATA
scrnatools-1.12.3.dist-info/WHEEL
scrnatools-1.12.3.dist-info/top_level.txt
scrnatools-1.12.3.dist-info/RECORD
