Metadata-Version: 2.1
Name: scrnatools
Version: 1.12.3
Summary: Tools for single cell RNA sequencing pipelines
Home-page: https://github.com/j-germino/sc-rna-tools
Author: Joe Germino
Author-email: joe.germino@ucsf.edu
Requires-Python: >=3,
License-File: LICENSE.txt
Requires-Dist: scanpy
Requires-Dist: scrublet
Requires-Dist: scvi-tools
Requires-Dist: matplotlib
Requires-Dist: pandas
Requires-Dist: numpy
Requires-Dist: seaborn
Requires-Dist: scikit-misc
Requires-Dist: leidenalg
Requires-Dist: anndata
Requires-Dist: scipy
Requires-Dist: starlette
